{
 "sample_id": "fives-101_g",
 "size": [
  768,
  768
 ],
 "material": "retina",
 "has_gt": true,
 "skeleton": {
  "nodes": [
   {
    "x": 448,
    "y": 28,
    "degree": 1
   },
   {
    "x": 305,
    "y": 30,
    "degree": 1
   },
   {
    "x": 490,
    "y": 62,
    "degree": 1
   },
   {
    "x": 218,
    "y": 69,
    "degree": 1
   },
   {
    "x": 172,
    "y": 85,
    "degree": 1
   },
   {
    "x": 370,
    "y": 92,
    "degree": 1
   },
   {
    "x": 621,
    "y": 110,
    "degree": 1
   },
   {
    "x": 288,
    "y": 135,
    "degree": 1
   },
   {
    "x": 84,
    "y": 161,
    "degree": 1
   },
   {
    "x": 458,
    "y": 190,
    "degree": 1
   },
   {
    "x": 431,
    "y": 252,
    "degree": 1
   },
   {
    "x": 432,
    "y": 254,
    "degree": 1
   },
   {
    "x": 432,
    "y": 255,
    "degree": 1
   },
   {
    "x": 434,
    "y": 261,
    "degree": 1
   },
   {
    "x": 206,
    "y": 280,
    "degree": 1
   },
   {
    "x": 90,
    "y": 282,
    "degree": 1
   },
   {
    "x": 114,
    "y": 285,
    "degree": 1
   },
   {
    "x": 737,
    "y": 288,
    "degree": 1
   },
   {
    "x": 232,
    "y": 296,
    "degree": 1
   },
   {
    "x": 395,
    "y": 297,
    "degree": 1
   },
   {
    "x": 398,
    "y": 299,
    "degree": 1
   },
   {
    "x": 405,
    "y": 303,
    "degree": 1
   },
   {
    "x": 408,
    "y": 305,
    "degree": 1
   },
   {
    "x": 388,
    "y": 335,
    "degree": 1
   },
   {
    "x": 255,
    "y": 343,
    "degree": 1
   },
   {
    "x": 405,
    "y": 346,
    "degree": 1
   },
   {
    "x": 452,
    "y": 347,
    "degree": 1
   },
   {
    "x": 338,
    "y": 369,
    "degree": 1
   },
   {
    "x": 517,
    "y": 380,
    "degree": 1
   },
   {
    "x": 328,
    "y": 395,
    "degree": 1
   },
   {
    "x": 525,
    "y": 396,
    "degree": 1
   },
   {
    "x": 482,
    "y": 401,
    "degree": 1
   },
   {
    "x": 533,
    "y": 411,
    "degree": 1
   },
   {
    "x": 352,
    "y": 421,
    "degree": 1
   },
   {
    "x": 522,
    "y": 432,
    "degree": 1
   },
   {
    "x": 268,
    "y": 437,
    "degree": 1
   },
   {
    "x": 488,
    "y": 446,
    "degree": 1
   },
   {
    "x": 464,
    "y": 447,
    "degree": 1
   },
   {
    "x": 498,
    "y": 449,
    "degree": 1
   },
   {
    "x": 215,
    "y": 501,
    "degree": 1
   },
   {
    "x": 82,
    "y": 538,
    "degree": 1
   },
   {
    "x": 686,
    "y": 551,
    "degree": 1
   },
   {
    "x": 76,
    "y": 554,
    "degree": 1
   },
   {
    "x": 322,
    "y": 596,
    "degree": 1
   },
   {
    "x": 112,
    "y": 642,
    "degree": 1
   },
   {
    "x": 586,
    "y": 663,
    "degree": 1
   },
   {
    "x": 209,
    "y": 712,
    "degree": 1
   },
   {
    "x": 473,
    "y": 740,
    "degree": 1
   },
   {
    "x": 456,
    "y": 111,
    "degree": 3
   },
   {
    "x": 460,
    "y": 113,
    "degree": 3
   },
   {
    "x": 461,
    "y": 113,
    "degree": 3
   },
   {
    "x": 460,
    "y": 114,
    "degree": 3
   },
   {
    "x": 457,
    "y": 117,
    "degree": 3
   },
   {
    "x": 458,
    "y": 117,
    "degree": 3
   },
   {
    "x": 457,
    "y": 118,
    "degree": 3
   },
   {
    "x": 374,
    "y": 122,
    "degree": 3
   },
   {
    "x": 296,
    "y": 135,
    "degree": 3
   },
   {
    "x": 219,
    "y": 151,
    "degree": 3
   },
   {
    "x": 122,
    "y": 164,
    "degree": 3
   },
   {
    "x": 395,
    "y": 228,
    "degree": 3
   },
   {
    "x": 394,
    "y": 229,
    "degree": 3
   },
   {
    "x": 395,
    "y": 229,
    "degree": 3
   },
   {
    "x": 119,
    "y": 249,
    "degree": 3
   },
   {
    "x": 429,
    "y": 265,
    "degree": 3
   },
   {
    "x": 430,
    "y": 265,
    "degree": 3
   },
   {
    "x": 430,
    "y": 266,
    "degree": 3
   },
   {
    "x": 113,
    "y": 276,
    "degree": 3
   },
   {
    "x": 291,
    "y": 292,
    "degree": 3
   },
   {
    "x": 291,
    "y": 293,
    "degree": 3
   },
   {
    "x": 292,
    "y": 293,
    "degree": 3
   },
   {
    "x": 476,
    "y": 336,
    "degree": 3
   },
   {
    "x": 476,
    "y": 337,
    "degree": 3
   },
   {
    "x": 477,
    "y": 337,
    "degree": 3
   },
   {
    "x": 406,
    "y": 339,
    "degree": 3
   },
   {
    "x": 407,
    "y": 339,
    "degree": 3
   },
   {
    "x": 406,
    "y": 340,
    "degree": 3
   },
   {
    "x": 490,
    "y": 345,
    "degree": 3
   },
   {
    "x": 491,
    "y": 345,
    "degree": 3
   },
   {
    "x": 491,
    "y": 346,
    "degree": 3
   },
   {
    "x": 502,
    "y": 358,
    "degree": 3
   },
   {
    "x": 502,
    "y": 384,
    "degree": 3
   },
   {
    "x": 502,
    "y": 385,
    "degree": 3
   },
   {
    "x": 503,
    "y": 385,
    "degree": 3
   },
   {
    "x": 501,
    "y": 387,
    "degree": 3
   },
   {
    "x": 500,
    "y": 388,
    "degree": 3
   },
   {
    "x": 501,
    "y": 388,
    "degree": 3
   },
   {
    "x": 488,
    "y": 401,
    "degree": 3
   },
   {
    "x": 489,
    "y": 401,
    "degree": 3
   },
   {
    "x": 489,
    "y": 402,
    "degree": 3
   },
   {
    "x": 493,
    "y": 407,
    "degree": 3
   },
   {
    "x": 521,
    "y": 407,
    "degree": 3
   },
   {
    "x": 429,
    "y": 408,
    "degree": 3
   },
   {
    "x": 494,
    "y": 408,
    "degree": 3
   },
   {
    "x": 495,
    "y": 408,
    "degree": 3
   },
   {
    "x": 521,
    "y": 408,
    "degree": 3
   },
   {
    "x": 522,
    "y": 408,
    "degree": 3
   },
   {
    "x": 428,
    "y": 409,
    "degree": 3
   },
   {
    "x": 431,
    "y": 409,
    "degree": 3
   },
   {
    "x": 495,
    "y": 409,
    "degree": 3
   },
   {
    "x": 427,
    "y": 410,
    "degree": 3
   },
   {
    "x": 428,
    "y": 410,
    "degree": 3
   },
   {
    "x": 519,
    "y": 410,
    "degree": 3
   },
   {
    "x": 429,
    "y": 411,
    "degree": 3
   },
   {
    "x": 441,
    "y": 411,
    "degree": 3
   },
   {
    "x": 430,
    "y": 412,
    "degree": 3
   },
   {
    "x": 441,
    "y": 412,
    "degree": 3
   },
   {
    "x": 442,
    "y": 412,
    "degree": 3
   },
   {
    "x": 497,
    "y": 420,
    "degree": 3
   },
   {
    "x": 498,
    "y": 420,
    "degree": 3
   },
   {
    "x": 497,
    "y": 421,
    "degree": 4
   },
   {
    "x": 497,
    "y": 422,
    "degree": 3
   },
   {
    "x": 498,
    "y": 422,
    "degree": 3
   },
   {
    "x": 495,
    "y": 429,
    "degree": 3
   },
   {
    "x": 512,
    "y": 429,
    "degree": 3
   },
   {
    "x": 514,
    "y": 431,
    "degree": 3
   },
   {
    "x": 515,
    "y": 431,
    "degree": 3
   },
   {
    "x": 514,
    "y": 432,
    "degree": 3
   },
   {
    "x": 484,
    "y": 443,
    "degree": 3
   },
   {
    "x": 484,
    "y": 444,
    "degree": 3
   },
   {
    "x": 485,
    "y": 444,
    "degree": 3
   },
   {
    "x": 482,
    "y": 446,
    "degree": 3
   },
   {
    "x": 401,
    "y": 479,
    "degree": 3
   },
   {
    "x": 402,
    "y": 479,
    "degree": 3
   },
   {
    "x": 401,
    "y": 480,
    "degree": 3
   },
   {
    "x": 358,
    "y": 533,
    "degree": 3
   },
   {
    "x": 88,
    "y": 552,
    "degree": 3
   },
   {
    "x": 509,
    "y": 606,
    "degree": 3
   },
   {
    "x": 509,
    "y": 607,
    "degree": 3
   },
   {
    "x": 510,
    "y": 607,
    "degree": 3
   },
   {
    "x": 278,
    "y": 614,
    "degree": 3
   },
   {
    "x": 279,
    "y": 614,
    "degree": 3
   },
   {
    "x": 279,
    "y": 615,
    "degree": 3
   },
   {
    "x": 219,
    "y": 618,
    "degree": 3
   },
   {
    "x": 219,
    "y": 619,
    "degree": 3
   },
   {
    "x": 220,
    "y": 619,
    "degree": 3
   }
  ],
  "edges": [
   {
    "polyline": [
     [
      448,
      30
     ],
     [
      448,
      33
     ],
     [
      449,
      36
     ],
     [
      449,
      39
     ],
     [
      449,
      42
     ],
     [
      449,
      45
     ],
     [
      449,
      48
     ],
     [
      449,
      51
     ],
     [
      448,
      54
     ],
     [
      448,
      57
     ],
     [
      448,
      60
     ],
     [
      448,
      63
     ],
     [
      448,
      66
     ],
     [
      448,
      69
     ],
     [
      448,
      72
     ],
     [
      448,
      75
     ],
     [
      448,
      78
     ],
     [
      448,
      81
     ],
     [
      449,
      84
     ],
     [
      449,
      87
     ],
     [
      449,
      90
     ],
     [
      449,
      93
     ],
     [
      450,
      96
     ],
     [
      451,
      99
     ],
     [
      452,
      102
     ],
     [
      454,
      105
     ],
     [
      454,
      108
     ]
    ],
    "length_px": 81,
    "mean_halfwidth_px": 2.0
   },
   {
    "polyline": [
     [
      306,
      31
     ],
     [
      308,
      35
     ],
     [
      309,
      39
     ],
     [
      310,
      43
     ],
     [
      311,
      47
     ],
     [
      313,
      51
     ],
     [
      314,
      55
     ],
     [
      316,
      59
     ],
     [
      317,
      63
     ],
     [
      318,
      67
     ],
     [
      321,
      71
     ],
     [
      324,
      75
     ],
     [
      327,
      79
     ],
     [
      330,
      83
     ],
     [
      333,
      87
     ],
     [
      337,
      91
     ],
     [
      340,
      94
     ],
     [
      343,
      97
     ],
     [
      347,
      101
     ],
     [
      350,
      104
     ],
     [
      354,
      106
     ],
     [
      358,
      110
     ],
     [
      362,
      113
     ],
     [
      365,
      116
     ],
     [
      369,
      119
     ],
     [
      373,
      121
     ]
    ],
    "length_px": 101,
    "mean_halfwidth_px": 2.24
   },
   {
    "polyline": [
     [
      489,
      63
     ],
     [
      488,
      65
     ],
     [
      487,
      67
     ],
     [
      486,
      69
     ],
     [
      486,
      71
     ],
     [
      485,
      73
     ],
     [
      485,
      75
     ],
     [
      485,
      77
     ],
     [
      484,
      79
     ],
     [
      483,
      81
     ],
     [
      481,
      83
     ],
     [
      480,
      85
     ],
     [
      479,
      87
     ],
     [
      478,
      89
     ],
     [
      477,
      91
     ],
     [
      475,
      93
     ],
     [
      474,
      95
     ],
     [
      473,
      97
     ],
     [
      472,
      99
     ],
     [
      470,
      101
     ],
     [
      469,
      103
     ],
     [
      467,
      105
     ],
     [
      466,
      107
     ],
     [
      464,
      109
     ],
     [
      463,
      111
     ]
    ],
    "length_px": 50,
    "mean_halfwidth_px": 1.41
   },
   {
    "polyline": [
     [
      220,
      70
     ],
     [
      223,
      71
     ],
     [
      225,
      73
     ],
     [
      228,
      76
     ],
     [
      231,
      78
     ],
     [
      233,
      81
     ],
     [
      235,
      84
     ],
     [
      238,
      87
     ],
     [
      241,
      89
     ],
     [
      242,
      92
     ],
     [
      244,
      95
     ],
     [
      246,
      98
     ],
     [
      247,
      101
     ],
     [
      249,
      104
     ],
     [
      251,
      106
     ],
     [
      254,
      109
     ],
     [
      257,
      112
     ],
     [
      260,
      115
     ],
     [
      263,
      116
     ],
     [
      266,
      118
     ],
     [
      269,
      119
     ],
     [
      272,
      119
     ],
     [
      275,
      120
     ],
     [
      278,
      121
     ],
     [
      281,
      123
     ],
     [
      284,
      124
     ],
     [
      287,
      127
     ],
     [
      290,
      128
     ],
     [
      293,
      129
     ],
     [
      295,
      132
     ]
    ],
    "length_px": 89,
    "mean_halfwidth_px": 1.41
   },
   {
    "polyline": [
     [
      173,
      87
     ],
     [
      173,
      89
     ],
     [
      174,
      91
     ],
     [
      176,
      92
     ],
     [
      178,
      94
     ],
     [
      180,
      96
     ],
     [
      182,
      98
     ],
     [
      184,
      99
     ],
     [
      186,
      101
     ],
     [
      188,
      103
     ],
     [
      190,
      103
     ],
     [
      192,
      105
     ],
     [
      194,
      107
     ],
     [
      195,
      109
     ],
     [
      197,
      110
     ],
     [
      199,
      112
     ],
     [
      201,
      114
     ],
     [
      202,
      116
     ],
     [
      203,
      118
     ],
     [
      205,
      120
     ],
     [
      205,
      122
     ],
     [
      206,
      124
     ],
     [
      208,
      126
     ],
     [
      209,
      128
     ],
     [
      211,
      130
     ],
     [
      212,
      132
     ],
     [
      213,
      134
     ],
     [
      214,
      136
     ],
     [
      215,
      138
     ],
     [
      217,
      140
     ],
     [
      217,
      142
     ],
     [
      218,
      144
     ],
     [
      219,
      146
     ],
     [
      219,
      148
     ]
    ],
    "length_px": 68,
    "mean_halfwidth_px": 2.0
   },
   {
    "polyline": [
     [
      370,
      94
     ],
     [
      371,
      95
     ],
     [
      371,
      96
     ],
     [
      372,
      97
     ],
     [
      373,
      98
     ],
     [
      374,
      99
     ],
     [
      374,
      100
     ],
     [
      374,
      101
     ],
     [
      374,
      102
     ],
     [
      374,
      103
     ],
     [
      374,
      104
     ],
     [
      374,
      105
     ],
     [
      374,
      106
     ],
     [
      375,
      107
     ],
     [
      375,
      108
     ],
     [
      375,
      109
     ],
     [
      375,
      110
     ],
     [
      376,
      111
     ],
     [
      376,
      112
     ],
     [
      376,
      113
     ],
     [
      376,
      114
     ],
     [
      376,
      115
     ],
     [
      376,
      116
     ],
     [
      376,
      117
     ],
     [
      375,
      118
     ],
     [
      375,
      119
     ],
     [
      375,
      120
     ],
     [
      375,
      121
     ]
    ],
    "length_px": 28,
    "mean_halfwidth_px": 2.0
   },
   {
    "polyline": [
     [
      458,
      111
     ],
     [
      459,
      112
     ]
    ],
    "length_px": 2,
    "mean_halfwidth_px": 1.41
   },
   {
    "polyline": [
     [
      620,
      111
     ],
     [
      615,
      120
     ],
     [
      610,
      129
     ],
     [
      605,
      138
     ],
     [
      598,
      147
     ],
     [
      592,
      156
     ],
     [
      586,
      165
     ],
     [
      577,
      174
     ],
     [
      570,
      183
     ],
     [
      564,
      192
     ],
     [
      555,
      201
     ],
     [
      547,
      210
     ],
     [
      541,
      219
     ],
     [
      534,
      227
     ],
     [
      528,
      235
     ],
     [
      519,
      243
     ],
     [
      511,
      251
     ],
     [
      503,
      260
     ],
     [
      498,
      269
     ],
     [
      496,
      278
     ],
     [
      493,
      287
     ],
     [
      491,
      296
     ],
     [
      491,
      305
     ],
     [
      491,
      314
     ],
     [
      491,
      323
     ],
     [
      491,
      332
     ],
     [
      493,
      341
     ]
    ],
    "length_px": 238,
    "mean_halfwidth_px": 2.24
   },
   {
    "polyline": [
     [
      455,
      112
     ],
     [
      456,
      113
     ],
     [
      456,
      114
     ],
     [
      456,
      115
     ],
     [
      456,
      116
     ]
    ],
    "length_px": 5,
    "mean_halfwidth_px": 1.0
   },
   {
    "polyline": [
     [
      457,
      120
     ],
     [
      457,
      122
     ],
     [
      457,
      124
     ],
     [
      457,
      126
     ],
     [
      457,
      128
     ],
     [
      457,
      130
     ],
     [
      457,
      132
     ],
     [
      457,
      134
     ],
     [
      457,
      136
     ],
     [
      457,
      138
     ],
     [
      457,
      140
     ],
     [
      457,
      142
     ],
     [
      457,
      144
     ],
     [
      457,
      146
     ],
     [
      458,
      148
     ],
     [
      458,
      150
     ],
     [
      458,
      152
     ],
     [
      458,
      154
     ],
     [
      458,
      156
     ],
     [
      458,
      158
     ],
     [
      458,
      160
     ],
     [
      457,
      162
     ],
     [
      457,
      164
     ],
     [
      457,
      166
     ],
     [
      458,
      168
     ],
     [
      458,
      170
     ],
     [
      458,
      172
     ],
     [
      458,
      174
     ],
     [
      458,
      176
     ],
     [
      458,
      178
     ],
     [
      458,
      180
     ],
     [
      458,
      182
     ],
     [
      458,
      184
     ],
     [
      458,
      186
     ],
     [
      458,
      188
     ]
    ],
    "length_px": 69,
    "mean_halfwidth_px": 2.0
   },
   {
    "polyline": [
     [
      375,
      123
     ],
     [
      376,
      128
     ],
     [
      378,
      133
     ],
     [
      379,
      138
     ],
     [
      380,
      143
     ],
     [
      381,
      148
     ],
     [
      383,
      153
     ],
     [
      385,
      158
     ],
     [
      387,
      163
     ],
     [
      388,
      168
     ],
     [
      390,
      173
     ],
     [
      392,
      178
     ],
     [
      394,
      183
     ],
     [
      396,
      188
     ],
     [
      397,
      193
     ],
     [
      399,
      198
     ],
     [
      401,
      203
     ],
     [
      403,
      208
     ],
     [
      405,
      213
     ],
     [
      407,
      218
     ],
     [
      412,
      222
     ],
     [
      416,
      227
     ],
     [
      419,
      232
     ],
     [
      420,
      237
     ],
     [
      423,
      242
     ],
     [
      427,
      247
     ]
    ],
    "length_px": 130,
    "mean_halfwidth_px": 2.0
   },
   {
    "polyline": [
     [
      289,
      136
     ],
     [
      290,
      136
     ],
     [
      291,
      136
     ],
     [
      292,
      136
     ],
     [
      293,
      136
     ],
     [
      294,
      136
     ],
     [
      295,
      136
     ]
    ],
    "length_px": 7,
    "mean_halfwidth_px": 1.0
   },
   {
    "polyline": [
     [
      297,
      136
     ],
     [
      301,
      137
     ],
     [
      305,
      139
     ],
     [
      309,
      143
     ],
     [
      312,
      146
     ],
     [
      316,
      149
     ],
     [
      320,
      153
     ],
     [
      324,
      156
     ],
     [
      328,
      159
     ],
     [
      332,
      163
     ],
     [
      336,
      164
     ],
     [
      340,
      165
     ],
     [
      344,
      167
     ],
     [
      348,
      170
     ],
     [
      352,
      174
     ],
     [
      355,
      178
     ],
     [
      358,
      181
     ],
     [
      361,
      185
     ],
     [
      365,
      188
     ],
     [
      368,
      192
     ],
     [
      372,
      196
     ],
     [
      375,
      200
     ],
     [
      379,
      204
     ],
     [
      382,
      208
     ],
     [
      385,
      212
     ],
     [
      388,
      216
     ],
     [
      391,
      220
     ],
     [
      394,
      224
     ]
    ],
    "length_px": 111,
    "mean_halfwidth_px": 1.41
   },
   {
    "polyline": [
     [
      123,
      163
     ],
     [
      127,
      163
     ],
     [
      131,
      163
     ],
     [
      135,
      162
     ],
     [
      139,
      162
     ],
     [
      143,
      162
     ],
     [
      147,
      162
     ],
     [
      151,
      161
     ],
     [
      155,
      160
     ],
     [
      159,
      160
     ],
     [
      163,
      160
     ],
     [
      167,
      160
     ],
     [
      171,
      160
     ],
     [
      175,
      159
     ],
     [
      179,
      159
     ],
     [
      183,
      158
     ],
     [
      187,
      157
     ],
     [
      191,
      156
     ],
     [
      195,
      156
     ],
     [
      199,
      155
     ],
     [
      203,
      155
     ],
     [
      207,
      154
     ],
     [
      211,
      154
     ],
     [
      215,
      153
     ]
    ],
    "length_px": 96,
    "mean_halfwidth_px": 3.0
   },
   {
    "polyline": [
     [
      220,
      152
     ],
     [
      227,
      153
     ],
     [
      234,
      155
     ],
     [
      241,
      157
     ],
     [
      248,
      159
     ],
     [
      255,
      162
     ],
     [
      262,
      165
     ],
     [
      269,
      168
     ],
     [
      276,
      170
     ],
     [
      283,
      173
     ],
     [
      290,
      177
     ],
     [
      297,
      180
     ],
     [
      304,
      182
     ],
     [
      311,
      184
     ],
     [
      318,
      187
     ],
     [
      325,
      189
     ],
     [
      332,
      193
     ],
     [
      339,
      198
     ],
     [
      346,
      202
     ],
     [
      353,
      204
     ],
     [
      360,
      207
     ],
     [
      367,
      211
     ],
     [
      374,
      216
     ],
     [
      381,
      221
     ],
     [
      388,
      227
     ]
    ],
    "length_px": 173,
    "mean_halfwidth_px": 3.16
   },
   {
    "polyline": [
     [
      86,
      160
     ],
     [
      87,
      160
     ],
     [
      88,
      160
     ],
     [
      89,
      159
     ],
     [
      90,
      159
     ],
     [
      91,
      159
     ],
     [
      92,
      159
     ],
     [
      93,
      159
     ],
     [
      94,
      159
     ],
     [
      95,
      159
     ],
     [
      96,
      159
     ],
     [
      97,
      159
     ],
     [
      98,
      159
     ],
     [
      99,
      159
     ],
     [
      100,
      159
     ],
     [
      101,
      159
     ],
     [
      102,
      159
     ],
     [
      103,
      159
     ],
     [
      104,
      159
     ],
     [
      105,
      160
     ],
     [
      106,
      160
     ],
     [
      107,
      160
     ],
     [
      108,
      160
     ],
     [
      109,
      160
     ],
     [
      110,
      161
     ],
     [
      111,
      161
     ],
     [
      112,
      161
     ],
     [
      113,
      161
     ],
     [
      114,
      161
     ],
     [
      115,
      161
     ],
     [
      116,
      161
     ],
     [
      117,
      162
     ],
     [
      118,
      162
     ],
     [
      119,
      162
     ],
     [
      120,
      162
     ],
     [
      121,
      163
     ]
    ],
    "length_px": 36,
    "mean_halfwidth_px": 3.0
   },
   {
    "polyline": [
     [
      121,
      165
     ],
     [
      120,
      168
     ],
     [
      120,
      171
     ],
     [
      118,
      174
     ],
     [
      115,
      177
     ],
     [
      114,
      180
     ],
     [
      113,
      183
     ],
     [
      112,
      186
     ],
     [
      112,
      189
     ],
     [
      112,
      192
     ],
     [
      112,
      195
     ],
     [
      112,
      198
     ],
     [
      112,
      201
     ],
     [
      112,
      204
     ],
     [
      112,
      207
     ],
     [
      112,
      210
     ],
     [
      112,
      213
     ],
     [
      113,
      216
     ],
     [
      113,
      219
     ],
     [
      114,
      222
     ],
     [
      115,
      225
     ],
     [
      116,
      228
     ],
     [
      115,
      231
     ],
     [
      116,
      234
     ],
     [
      117,
      237
     ],
     [
      118,
      240
     ],
     [
      118,
      243
     ],
     [
      118,
      246
     ]
    ],
    "length_px": 84,
    "mean_halfwidth_px": 1.41
   },
   {
    "polyline": [
     [
      396,
      230
     ],
     [
      397,
      231
     ],
     [
      398,
      231
     ],
     [
      399,
      231
     ],
     [
      400,
      232
     ],
     [
      401,
      233
     ],
     [
      402,
      234
     ],
     [
      403,
      235
     ],
     [
      404,
      236
     ],
     [
      405,
      236
     ],
     [
      406,
      237
     ],
     [
      407,
      238
     ],
     [
      407,
      239
     ],
     [
      408,
      240
     ],
     [
      409,
      241
     ],
     [
      410,
      242
     ],
     [
      411,
      243
     ],
     [
      411,
      244
     ],
     [
      412,
      245
     ],
     [
      413,
      246
     ],
     [
      413,
      247
     ],
     [
      414,
      248
     ],
     [
      415,
      249
     ],
     [
      416,
      250
     ],
     [
      416,
      251
     ],
     [
      417,
      252
     ],
     [
      418,
      253
     ],
     [
      419,
      254
     ],
     [
      420,
      254
     ],
     [
      421,
      255
     ],
     [
      421,
      256
     ],
     [
      422,
      257
     ],
     [
      423,
      258
     ],
     [
      424,
      259
     ],
     [
      425,
      260
     ],
     [
      425,
      261
     ],
     [
      426,
      262
     ],
     [
      427,
      263
     ],
     [
      427,
      264
     ]
    ],
    "length_px": 39,
    "mean_halfwidth_px": 2.83
   },
   {
    "polyline": [
     [
      118,
      250
     ],
     [
      118,
      251
     ],
     [
      118,
      252
     ],
     [
      118,
      253
     ],
     [
      118,
      254
     ],
     [
      118,
      255
     ],
     [
      118,
      256
     ],
     [
      118,
      257
     ],
     [
      118,
      258
     ],
     [
      118,
      259
     ],
     [
      118,
      260
     ],
     [
      118,
      261
     ],
     [
      118,
      262
     ],
     [
      117,
      263
     ],
     [
      117,
      264
     ],
     [
      117,
      265
     ],
     [
      117,
      266
     ],
     [
      117,
      267
     ],
     [
      117,
      268
     ],
     [
      117,
      269
     ],
     [
      116,
      270
     ],
     [
      116,
      271
     ],
     [
      116,
      272
     ],
     [
      115,
      273
     ],
     [
      115,
      274
     ],
     [
      114,
      275
     ]
    ],
    "length_px": 26,
    "mean_halfwidth_px": 1.71
   },
   {
    "polyline": [
     [
      121,
      250
     ],
     [
      124,
      251
     ],
     [
      127,
      252
     ],
     [
      130,
      253
     ],
     [
      133,
      254
     ],
     [
      136,
      256
     ],
     [
      139,
      257
     ],
     [
      142,
      259
     ],
     [
      145,
      259
     ],
     [
      148,
      259
     ],
     [
      151,
      259
     ],
     [
      154,
      260
     ],
     [
      157,
      262
     ],
     [
      160,
      264
     ],
     [
      163,
      265
     ],
     [
      166,
      265
     ],
     [
      169,
      266
     ],
     [
      172,
      267
     ],
     [
      175,
      268
     ],
     [
      178,
      270
     ],
     [
      181,
      272
     ],
     [
      184,
      274
     ],
     [
      187,
      275
     ],
     [
      190,
      277
     ],
     [
      193,
      278
     ],
     [
      196,
      278
     ],
     [
      199,
      278
     ],
     [
      202,
      279
     ]
    ],
    "length_px": 84,
    "mean_halfwidth_px": 1.41
   },
   {
    "polyline": [
     [
      432,
      262
     ],
     [
      432,
      263
     ],
     [
      431,
      264
     ]
    ],
    "length_px": 3,
    "mean_halfwidth_px": 1.0
   },
   {
    "polyline": [
     [
      431,
      268
     ],
     [
      432,
      270
     ],
     [
      434,
      272
     ],
     [
      436,
      274
     ],
     [
      437,
      276
     ],
     [
      439,
      278
     ],
     [
      441,
      280
     ],
     [
      442,
      282
     ],
     [
      444,
      284
     ],
     [
      445,
      286
     ],
     [
      446,
      288
     ],
     [
      447,
      290
     ],
     [
      449,
      292
     ],
     [
      451,
      294
     ],
     [
      453,
      296
     ],
     [
      455,
      298
     ],
     [
      456,
      300
     ],
     [
      458,
      302
     ],
     [
      460,
      304
     ],
     [
      462,
      306
     ],
     [
      463,
      308
     ],
     [
      464,
      310
     ],
     [
      465,
      312
     ],
     [
      466,
      314
     ],
     [
      468,
      316
     ],
     [
      468,
      318
     ],
     [
      469,
      320
     ],
     [
      470,
      322
     ],
     [
      471,
      324
     ],
     [
      472,
      326
     ],
     [
      473,
      328
     ],
     [
      475,
      330
     ],
     [
      476,
      332
     ],
     [
      476,
      334
     ]
    ],
    "length_px": 67,
    "mean_halfwidth_px": 3.61
   },
   {
    "polyline": [
     [
      503,
      357
     ],
     [
      507,
      347
     ],
     [
      510,
      337
     ],
     [
      515,
      327
     ],
     [
      525,
      319
     ],
     [
      535,
      314
     ],
     [
      545,
      310
     ],
     [
      555,
      306
     ],
     [
      565,
      300
     ],
     [
      575,
      295
     ],
     [
      585,
      290
     ],
     [
      595,
      285
     ],
     [
      605,
      281
     ],
     [
      615,
      278
     ],
     [
      625,
      275
     ],
     [
      635,
      273
     ],
     [
      645,
      270
     ],
     [
      655,
      270
     ],
     [
      665,
      272
     ],
     [
      675,
      274
     ],
     [
      685,
      276
     ],
     [
      695,
      279
     ],
     [
      705,
      281
     ],
     [
      715,
      283
     ],
     [
      725,
      285
     ],
     [
      735,
      288
     ]
    ],
    "length_px": 251,
    "mean_halfwidth_px": 3.0
   },
   {
    "polyline": [
     [
      92,
      282
     ],
     [
      93,
      282
     ],
     [
      94,
      281
     ],
     [
      95,
      281
     ],
     [
      96,
      280
     ],
     [
      97,
      280
     ],
     [
      98,
      280
     ],
     [
      99,
      280
     ],
     [
      100,
      280
     ],
     [
      101,
      280
     ],
     [
      102,
      280
     ],
     [
      103,
      280
     ],
     [
      104,
      280
     ],
     [
      105,
      280
     ],
     [
      106,
      279
     ],
     [
      107,
      279
     ],
     [
      108,
      278
     ],
     [
      109,
      277
     ],
     [
      110,
      277
     ],
     [
      111,
      277
     ],
     [
      112,
      277
     ]
    ],
    "length_px": 21,
    "mean_halfwidth_px": 1.0
   },
   {
    "polyline": [
     [
      114,
      277
     ],
     [
      114,
      278
     ],
     [
      114,
      279
     ],
     [
      114,
      280
     ],
     [
      114,
      281
     ],
     [
      114,
      282
     ],
     [
      114,
      283
     ]
    ],
    "length_px": 7,
    "mean_halfwidth_px": 1.0
   },
   {
    "polyline": [
     [
      293,
      292
     ],
     [
      297,
      291
     ],
     [
      301,
      290
     ],
     [
      305,
      290
     ],
     [
      309,
      289
     ],
     [
      313,
      289
     ],
     [
      317,
      290
     ],
     [
      321,
      292
     ],
     [
      325,
      292
     ],
     [
      329,
      291
     ],
     [
      333,
      290
     ],
     [
      337,
      289
     ],
     [
      341,
      290
     ],
     [
      345,
      289
     ],
     [
      349,
      286
     ],
     [
      353,
      285
     ],
     [
      357,
      285
     ],
     [
      361,
      285
     ],
     [
      365,
      285
     ],
     [
      369,
      285
     ],
     [
      373,
      285
     ],
     [
      377,
      286
     ],
     [
      381,
      288
     ],
     [
      385,
      291
     ],
     [
      389,
      294
     ],
     [
      393,
      296
     ]
    ],
    "length_px": 101,
    "mean_halfwidth_px": 2.0
   },
   {
    "polyline": [
     [
      234,
      295
     ],
     [
      236,
      295
     ],
     [
      238,
      295
     ],
     [
      240,
      295
     ],
     [
      242,
      295
     ],
     [
      244,
      295
     ],
     [
      246,
      295
     ],
     [
      248,
      295
     ],
     [
      250,
      294
     ],
     [
      252,
      294
     ],
     [
      254,
      293
     ],
     [
      256,
      293
     ],
     [
      258,
      293
     ],
     [
      260,
      293
     ],
     [
      262,
      293
     ],
     [
      264,
      292
     ],
     [
      266,
      292
     ],
     [
      268,
      292
     ],
     [
      270,
      291
     ],
     [
      272,
      291
     ],
     [
      274,
      290
     ],
     [
      276,
      290
     ],
     [
      278,
      290
     ],
     [
      280,
      290
     ],
     [
      282,
      290
     ],
     [
      284,
      290
     ],
     [
      286,
      290
     ],
     [
      288,
      290
     ],
     [
      290,
      291
     ]
    ],
    "length_px": 57,
    "mean_halfwidth_px": 1.0
   },
   {
    "polyline": [
     [
      290,
      294
     ],
     [
      289,
      296
     ],
     [
      288,
      298
     ],
     [
      286,
      300
     ],
     [
      284,
      302
     ],
     [
      283,
      304
     ],
     [
      281,
      306
     ],
     [
      279,
      307
     ],
     [
      277,
      308
     ],
     [
      276,
      310
     ],
     [
      274,
      312
     ],
     [
      273,
      314
     ],
     [
      271,
      316
     ],
     [
      270,
      318
     ],
     [
      268,
      319
     ],
     [
      267,
      321
     ],
     [
      265,
      323
     ],
     [
      265,
      325
     ],
     [
      264,
      327
     ],
     [
      263,
      329
     ],
     [
      263,
      331
     ],
     [
      262,
      333
     ],
     [
      262,
      335
     ],
     [
      261,
      337
     ],
     [
      259,
      339
     ],
     [
      257,
      341
     ]
    ],
    "length_px": 52,
    "mean_halfwidth_px": 1.41
   },
   {
    "polyline": [
     [
      400,
      300
     ],
     [
      401,
      300
     ],
     [
      402,
      301
     ],
     [
      403,
      302
     ],
     [
      404,
      302
     ]
    ],
    "length_px": 5,
    "mean_halfwidth_px": 1.0
   },
   {
    "polyline": [
     [
      410,
      306
     ],
     [
      412,
      308
     ],
     [
      414,
      308
     ],
     [
      416,
      310
     ],
     [
      418,
      311
     ],
     [
      420,
      313
     ],
     [
      422,
      314
     ],
     [
      424,
      315
     ],
     [
      426,
      317
     ],
     [
      428,
      319
     ],
     [
      430,
      321
     ],
     [
      432,
      323
     ],
     [
      433,
      325
     ],
     [
      435,
      327
     ],
     [
      437,
      327
     ],
     [
      439,
      328
     ],
     [
      441,
      330
     ],
     [
      443,
      331
     ],
     [
      445,
      332
     ],
     [
      447,
      333
     ],
     [
      449,
      334
     ],
     [
      451,
      335
     ],
     [
      453,
      337
     ],
     [
      455,
      337
     ],
     [
      457,
      338
     ],
     [
      459,
      338
     ],
     [
      461,
      339
     ],
     [
      463,
      340
     ],
     [
      465,
      340
     ],
     [
      467,
      340
     ],
     [
      469,
      340
     ],
     [
      471,
      340
     ],
     [
      473,
      340
     ],
     [
      475,
      338
     ]
    ],
    "length_px": 67,
    "mean_halfwidth_px": 1.41
   },
   {
    "polyline": [
     [
      390,
      335
     ],
     [
      391,
      334
     ],
     [
      392,
      333
     ],
     [
      393,
      333
     ],
     [
      394,
      333
     ],
     [
      395,
      333
     ],
     [
      396,
      333
     ],
     [
      397,
      333
     ],
     [
      398,
      334
     ],
     [
      399,
      334
     ],
     [
      400,
      334
     ],
     [
      401,
      335
     ],
     [
      402,
      335
     ],
     [
      403,
      336
     ],
     [
      404,
      337
     ],
     [
      405,
      338
     ]
    ],
    "length_px": 16,
    "mean_halfwidth_px": 2.0
   },
   {
    "polyline": [
     [
      479,
      338
     ],
     [
      480,
      339
     ],
     [
      481,
      340
     ],
     [
      481,
      341
     ],
     [
      482,
      342
     ],
     [
      483,
      343
     ],
     [
      484,
      343
     ],
     [
      485,
      344
     ],
     [
      486,
      344
     ],
     [
      487,
      344
     ],
     [
      488,
      345
     ]
    ],
    "length_px": 11,
    "mean_halfwidth_px": 5.0
   },
   {
    "polyline": [
     [
      409,
      339
     ],
     [
      410,
      339
     ],
     [
      411,
      339
     ],
     [
      412,
      340
     ],
     [
      413,
      340
     ],
     [
      414,
      340
     ],
     [
      415,
      340
     ],
     [
      416,
      341
     ],
     [
      417,
      341
     ],
     [
      418,
      341
     ],
     [
      419,
      342
     ],
     [
      420,
      342
     ],
     [
      421,
      342
     ],
     [
      422,
      343
     ],
     [
      423,
      343
     ],
     [
      424,
      343
     ],
     [
      425,
      344
     ],
     [
      426,
      344
     ],
     [
      427,
      344
     ],
     [
      428,
      345
     ],
     [
      429,
      345
     ],
     [
      430,
      345
     ],
     [
      431,
      346
     ],
     [
      432,
      346
     ],
     [
      433,
      346
     ],
     [
      434,
      346
     ],
     [
      435,
      346
     ],
     [
      436,
      346
     ],
     [
      437,
      346
     ],
     [
      438,
      347
     ],
     [
      439,
      347
     ],
     [
      440,
      347
     ],
     [
      441,
      347
     ],
     [
      442,
      347
     ],
     [
      443,
      347
     ],
     [
      444,
      347
     ],
     [
      445,
      347
     ],
     [
      446,
      348
     ],
     [
      447,
      348
     ],
     [
      448,
      348
     ],
     [
      449,
      348
     ],
     [
      450,
      348
     ],
     [
      451,
      348
     ]
    ],
    "length_px": 43,
    "mean_halfwidth_px": 1.41
   },
   {
    "polyline": [
     [
      405,
      341
     ],
     [
      405,
      342
     ],
     [
      405,
      343
     ],
     [
      405,
      344
     ]
    ],
    "length_px": 4,
    "mean_halfwidth_px": 1.0
   },
   {
    "polyline": [
     [
      492,
      348
     ],
     [
      493,
      349
     ],
     [
      493,
      350
     ],
     [
      494,
      351
     ],
     [
      495,
      352
     ],
     [
      496,
      353
     ],
     [
      497,
      354
     ],
     [
      497,
      355
     ],
     [
      498,
      356
     ],
     [
      499,
      356
     ],
     [
      500,
      357
     ],
     [
      501,
      357
     ]
    ],
    "length_px": 12,
    "mean_halfwidth_px": 6.4
   },
   {
    "polyline": [
     [
      501,
      359
     ],
     [
      502,
      360
     ],
     [
      502,
      361
     ],
     [
      502,
      362
     ],
     [
      502,
      363
     ],
     [
      502,
      364
     ],
     [
      502,
      365
     ],
     [
      502,
      366
     ],
     [
      502,
      367
     ],
     [
      502,
      368
     ],
     [
      502,
      369
     ],
     [
      502,
      370
     ],
     [
      502,
      371
     ],
     [
      502,
      372
     ],
     [
      502,
      373
     ],
     [
      502,
      374
     ],
     [
      502,
      375
     ],
     [
      502,
      376
     ],
     [
      502,
      377
     ],
     [
      502,
      378
     ],
     [
      502,
      379
     ],
     [
      502,
      380
     ],
     [
      502,
      381
     ],
     [
      502,
      382
     ]
    ],
    "length_px": 24,
    "mean_halfwidth_px": 5.0
   },
   {
    "polyline": [
     [
      340,
      369
     ],
     [
      343,
      370
     ],
     [
      346,
      370
     ],
     [
      349,
      370
     ],
     [
      352,
      371
     ],
     [
      355,
      371
     ],
     [
      358,
      372
     ],
     [
      361,
      373
     ],
     [
      364,
      373
     ],
     [
      367,
      374
     ],
     [
      370,
      375
     ],
     [
      373,
      377
     ],
     [
      376,
      379
     ],
     [
      379,
      381
     ],
     [
      382,
      383
     ],
     [
      385,
      385
     ],
     [
      388,
      388
     ],
     [
      391,
      388
     ],
     [
      394,
      390
     ],
     [
      397,
      391
     ],
     [
      400,
      393
     ],
     [
      403,
      394
     ],
     [
      406,
      395
     ],
     [
      409,
      397
     ],
     [
      412,
      399
     ],
     [
      415,
      400
     ],
     [
      418,
      402
     ],
     [
      421,
      404
     ],
     [
      424,
      405
     ],
     [
      427,
      407
     ]
    ],
    "length_px": 89,
    "mean_halfwidth_px": 1.0
   },
   {
    "polyline": [
     [
      516,
      382
     ],
     [
      515,
      383
     ],
     [
      514,
      384
     ],
     [
      514,
      385
     ],
     [
      513,
      386
     ],
     [
      512,
      387
     ],
     [
      511,
      388
     ],
     [
      510,
      388
     ],
     [
      509,
      388
     ],
     [
      508,
      387
     ],
     [
      507,
      387
     ],
     [
      506,
      387
     ],
     [
      505,
      387
     ],
     [
      504,
      386
     ]
    ],
    "length_px": 14,
    "mean_halfwidth_px": 1.0
   },
   {
    "polyline": [
     [
      499,
      389
     ],
     [
      498,
      389
     ],
     [
      497,
      390
     ],
     [
      496,
      391
     ],
     [
      495,
      392
     ],
     [
      495,
      393
     ],
     [
      494,
      394
     ],
     [
      493,
      395
     ],
     [
      493,
      396
     ],
     [
      492,
      397
     ],
     [
      491,
      398
     ],
     [
      490,
      399
     ],
     [
      490,
      400
     ]
    ],
    "length_px": 13,
    "mean_halfwidth_px": 2.83
   },
   {
    "polyline": [
     [
      502,
      389
     ],
     [
      503,
      390
     ],
     [
      503,
      391
     ],
     [
      503,
      392
     ],
     [
      503,
      393
     ],
     [
      503,
      394
     ],
     [
      503,
      395
     ],
     [
      503,
      396
     ],
     [
      503,
      397
     ],
     [
      502,
      398
     ],
     [
      501,
      399
     ],
     [
      501,
      400
     ],
     [
      500,
      401
     ],
     [
      500,
      402
     ],
     [
      499,
      403
     ],
     [
      499,
      404
     ],
     [
      498,
      405
     ],
     [
      497,
      406
     ],
     [
      496,
      407
     ]
    ],
    "length_px": 19,
    "mean_halfwidth_px": 3.0
   },
   {
    "polyline": [
     [
      425,
      410
     ],
     [
      421,
      410
     ],
     [
      417,
      409
     ],
     [
      413,
      409
     ],
     [
      409,
      409
     ],
     [
      405,
      407
     ],
     [
      401,
      407
     ],
     [
      397,
      406
     ],
     [
      393,
      406
     ],
     [
      389,
      407
     ],
     [
      385,
      407
     ],
     [
      381,
      409
     ],
     [
      377,
      408
     ],
     [
      373,
      408
     ],
     [
      369,
      405
     ],
     [
      365,
      404
     ],
     [
      361,
      404
     ],
     [
      357,
      404
     ],
     [
      353,
      404
     ],
     [
      349,
      402
     ],
     [
      345,
      401
     ],
     [
      341,
      400
     ],
     [
      337,
      398
     ],
     [
      333,
      396
     ]
    ],
    "length_px": 96,
    "mean_halfwidth_px": 1.41
   },
   {
    "polyline": [
     [
      524,
      397
     ],
     [
      523,
      398
     ],
     [
      523,
      399
     ],
     [
      523,
      400
     ],
     [
      523,
      401
     ],
     [
      522,
      402
     ],
     [
      522,
      403
     ],
     [
      522,
      404
     ],
     [
      521,
      405
     ]
    ],
    "length_px": 9,
    "mean_halfwidth_px": 1.0
   },
   {
    "polyline": [
     [
      486,
      401
     ],
     [
      485,
      401
     ],
     [
      484,
      401
     ]
    ],
    "length_px": 3,
    "mean_halfwidth_px": 4.0
   },
   {
    "polyline": [
     [
      490,
      403
     ],
     [
      491,
      404
     ],
     [
      492,
      405
     ],
     [
      492,
      406
     ]
    ],
    "length_px": 4,
    "mean_halfwidth_px": 5.05
   },
   {
    "polyline": [
     [
      492,
      408
     ],
     [
      490,
      410
     ],
     [
      488,
      410
     ],
     [
      486,
      411
     ],
     [
      484,
      411
     ],
     [
      482,
      411
     ],
     [
      480,
      412
     ],
     [
      478,
      412
     ],
     [
      476,
      413
     ],
     [
      474,
      413
     ],
     [
      472,
      413
     ],
     [
      470,
      413
     ],
     [
      468,
      413
     ],
     [
      466,
      412
     ],
     [
      464,
      412
     ],
     [
      462,
      412
     ],
     [
      460,
      412
     ],
     [
      458,
      412
     ],
     [
      456,
      412
     ],
     [
      454,
      412
     ],
     [
      452,
      412
     ],
     [
      450,
      412
     ],
     [
      448,
      412
     ],
     [
      446,
      412
     ],
     [
      444,
      412
     ]
    ],
    "length_px": 49,
    "mean_halfwidth_px": 2.0
   },
   {
    "polyline": [
     [
      518,
      409
     ],
     [
      517,
      408
     ],
     [
      516,
      409
     ],
     [
      515,
      409
     ],
     [
      514,
      410
     ],
     [
      513,
      410
     ],
     [
      512,
      411
     ],
     [
      511,
      412
     ],
     [
      510,
      413
     ],
     [
      509,
      413
     ],
     [
      508,
      414
     ],
     [
      507,
      414
     ],
     [
      506,
      414
     ],
     [
      505,
      414
     ],
     [
      504,
      414
     ],
     [
      503,
      415
     ],
     [
      502,
      416
     ],
     [
      501,
      417
     ],
     [
      500,
      418
     ],
     [
      499,
      419
     ]
    ],
    "length_px": 20,
    "mean_halfwidth_px": 1.0
   },
   {
    "polyline": [
     [
      440,
      410
     ],
     [
      439,
      410
     ],
     [
      438,
      410
     ],
     [
      437,
      410
     ],
     [
      436,
      410
     ],
     [
      435,
      410
     ],
     [
      434,
      409
     ],
     [
      433,
      409
     ]
    ],
    "length_px": 8,
    "mean_halfwidth_px": 1.0
   },
   {
    "polyline": [
     [
      524,
      409
     ],
     [
      525,
      409
     ],
     [
      526,
      410
     ],
     [
      527,
      410
     ],
     [
      528,
      410
     ],
     [
      529,
      411
     ],
     [
      530,
      411
     ],
     [
      531,
      411
     ]
    ],
    "length_px": 8,
    "mean_halfwidth_px": 1.21
   },
   {
    "polyline": [
     [
      495,
      411
     ],
     [
      495,
      412
     ],
     [
      495,
      413
     ],
     [
      495,
      414
     ],
     [
      495,
      415
     ],
     [
      496,
      416
     ],
     [
      496,
      417
     ],
     [
      496,
      418
     ],
     [
      496,
      419
     ]
    ],
    "length_px": 9,
    "mean_halfwidth_px": 7.0
   },
   {
    "polyline": [
     [
      440,
      413
     ],
     [
      439,
      413
     ],
     [
      438,
      413
     ],
     [
      437,
      413
     ],
     [
      436,
      413
     ],
     [
      435,
      413
     ],
     [
      434,
      413
     ],
     [
      433,
      412
     ],
     [
      432,
      412
     ]
    ],
    "length_px": 9,
    "mean_halfwidth_px": 1.0
   },
   {
    "polyline": [
     [
      518,
      412
     ],
     [
      518,
      413
     ],
     [
      517,
      414
     ],
     [
      517,
      415
     ],
     [
      516,
      416
     ],
     [
      516,
      417
     ],
     [
      515,
      418
     ],
     [
      515,
      419
     ],
     [
      514,
      420
     ],
     [
      514,
      421
     ],
     [
      513,
      422
     ],
     [
      513,
      423
     ],
     [
      513,
      424
     ],
     [
      513,
      425
     ],
     [
      512,
      426
     ],
     [
      513,
      427
     ],
     [
      513,
      428
     ]
    ],
    "length_px": 17,
    "mean_halfwidth_px": 1.41
   },
   {
    "polyline": [
     [
      354,
      420
     ],
     [
      357,
      420
     ],
     [
      360,
      420
     ],
     [
      363,
      419
     ],
     [
      366,
      419
     ],
     [
      369,
      418
     ],
     [
      372,
      417
     ],
     [
      375,
      417
     ],
     [
      378,
      416
     ],
     [
      381,
      415
     ],
     [
      384,
      414
     ],
     [
      387,
      414
     ],
     [
      390,
      415
     ],
     [
      393,
      414
     ],
     [
      396,
      414
     ],
     [
      399,
      413
     ],
     [
      402,
      413
     ],
     [
      405,
      413
     ],
     [
      408,
      413
     ],
     [
      411,
      413
     ],
     [
      414,
      413
     ],
     [
      417,
      413
     ],
     [
      420,
      413
     ],
     [
      423,
      414
     ],
     [
      426,
      413
     ],
     [
      429,
      413
     ]
    ],
    "length_px": 76,
    "mean_halfwidth_px": 1.0
   },
   {
    "polyline": [
     [
      496,
      423
     ],
     [
      496,
      424
     ],
     [
      495,
      425
     ],
     [
      495,
      426
     ],
     [
      495,
      427
     ]
    ],
    "length_px": 5,
    "mean_halfwidth_px": 7.0
   },
   {
    "polyline": [
     [
      499,
      423
     ],
     [
      500,
      424
     ],
     [
      501,
      425
     ],
     [
      502,
      426
     ],
     [
      503,
      426
     ],
     [
      504,
      426
     ],
     [
      505,
      426
     ],
     [
      506,
      427
     ],
     [
      507,
      427
     ],
     [
      508,
      428
     ],
     [
      509,
      428
     ],
     [
      510,
      428
     ]
    ],
    "length_px": 12,
    "mean_halfwidth_px": 3.08
   },
   {
    "polyline": [
     [
      494,
      430
     ],
     [
      493,
      431
     ],
     [
      492,
      432
     ],
     [
      491,
      433
     ],
     [
      490,
      434
     ],
     [
      489,
      435
     ],
     [
      488,
      436
     ],
     [
      487,
      437
     ],
     [
      486,
      438
     ],
     [
      485,
      439
     ],
     [
      485,
      440
     ],
     [
      485,
      441
     ],
     [
      485,
      442
     ]
    ],
    "length_px": 13,
    "mean_halfwidth_px": 3.16
   },
   {
    "polyline": [
     [
      496,
      430
     ],
     [
      497,
      431
     ],
     [
      498,
      432
     ],
     [
      498,
      433
     ],
     [
      498,
      434
     ],
     [
      498,
      435
     ],
     [
      499,
      436
     ],
     [
      499,
      437
     ],
     [
      499,
      438
     ],
     [
      499,
      439
     ],
     [
      499,
      440
     ],
     [
      499,
      441
     ],
     [
      499,
      442
     ],
     [
      498,
      443
     ],
     [
      498,
      444
     ],
     [
      498,
      445
     ],
     [
      498,
      446
     ],
     [
      498,
      447
     ]
    ],
    "length_px": 18,
    "mean_halfwidth_px": 3.0
   },
   {
    "polyline": [
     [
      520,
      432
     ],
     [
      519,
      431
     ],
     [
      518,
      431
     ],
     [
      517,
      431
     ]
    ],
    "length_px": 4,
    "mean_halfwidth_px": 1.5
   },
   {
    "polyline": [
     [
      514,
      434
     ],
     [
      518,
      441
     ],
     [
      523,
      448
     ],
     [
      529,
      455
     ],
     [
      535,
      461
     ],
     [
      542,
      468
     ],
     [
      548,
      475
     ],
     [
      555,
      481
     ],
     [
      562,
      487
     ],
     [
      569,
      493
     ],
     [
      576,
      498
     ],
     [
      583,
      504
     ],
     [
      590,
      509
     ],
     [
      597,
      514
     ],
     [
      604,
      518
     ],
     [
      611,
      520
     ],
     [
      618,
      522
     ],
     [
      625,
      525
     ],
     [
      632,
      528
     ],
     [
      639,
      532
     ],
     [
      646,
      535
     ],
     [
      653,
      539
     ],
     [
      660,
      541
     ],
     [
      667,
      543
     ],
     [
      674,
      547
     ],
     [
      681,
      549
     ]
    ],
    "length_px": 179,
    "mean_halfwidth_px": 2.0
   },
   {
    "polyline": [
     [
      400,
      478
     ],
     [
      395,
      473
     ],
     [
      390,
      469
     ],
     [
      385,
      466
     ],
     [
      380,
      465
     ],
     [
      375,
      465
     ],
     [
      370,
      467
     ],
     [
      365,
      467
     ],
     [
      360,
      468
     ],
     [
      355,
      469
     ],
     [
      350,
      468
     ],
     [
      345,
      468
     ],
     [
      340,
      469
     ],
     [
      335,
      470
     ],
     [
      330,
      470
     ],
     [
      325,
      470
     ],
     [
      320,
      470
     ],
     [
      315,
      467
     ],
     [
      310,
      464
     ],
     [
      305,
      461
     ],
     [
      300,
      458
     ],
     [
      295,
      455
     ],
     [
      290,
      451
     ],
     [
      285,
      448
     ],
     [
      280,
      446
     ],
     [
      275,
      443
     ],
     [
      270,
      440
     ]
    ],
    "length_px": 133,
    "mean_halfwidth_px": 1.41
   },
   {
    "polyline": [
     [
      481,
      445
     ],
     [
      474,
      447
     ],
     [
      470,
      454
     ],
     [
      464,
      461
     ],
     [
      459,
      468
     ],
     [
      454,
      475
     ],
     [
      449,
      482
     ],
     [
      442,
      489
     ],
     [
      436,
      496
     ],
     [
      430,
      503
     ],
     [
      424,
      510
     ],
     [
      417,
      516
     ],
     [
      410,
      522
     ],
     [
      404,
      528
     ],
     [
      399,
      535
     ],
     [
      394,
      542
     ],
     [
      387,
      548
     ],
     [
      380,
      553
     ],
     [
      373,
      559
     ],
     [
      367,
      565
     ],
     [
      361,
      572
     ],
     [
      356,
      579
     ],
     [
      350,
      585
     ],
     [
      343,
      590
     ],
     [
      336,
      593
     ],
     [
      329,
      596
     ]
    ],
    "length_px": 181,
    "mean_halfwidth_px": 1.41
   },
   {
    "polyline": [
     [
      462,
      447
     ],
     [
      460,
      447
     ],
     [
      458,
      446
     ],
     [
      456,
      446
     ],
     [
      454,
      447
     ],
     [
      452,
      447
     ],
     [
      450,
      448
     ],
     [
      448,
      449
     ],
     [
      446,
      450
     ],
     [
      444,
      451
     ],
     [
      442,
      452
     ],
     [
      440,
      453
     ],
     [
      438,
      455
     ],
     [
      436,
      456
     ],
     [
      434,
      457
     ],
     [
      432,
      459
     ],
     [
      430,
      461
     ],
     [
      428,
      462
     ],
     [
      426,
      463
     ],
     [
      424,
      465
     ],
     [
      422,
      466
     ],
     [
      420,
      468
     ],
     [
      418,
      469
     ],
     [
      416,
      470
     ],
     [
      414,
      471
     ],
     [
      412,
      473
     ],
     [
      410,
      474
     ],
     [
      408,
      475
     ],
     [
      406,
      476
     ],
     [
      404,
      478
     ]
    ],
    "length_px": 60,
    "mean_halfwidth_px": 3.61
   },
   {
    "polyline": [
     [
      482,
      448
     ],
     [
      482,
      454
     ],
     [
      481,
      460
     ],
     [
      480,
      466
     ],
     [
      480,
      472
     ],
     [
      480,
      478
     ],
     [
      480,
      484
     ],
     [
      481,
      490
     ],
     [
      481,
      496
     ],
     [
      481,
      502
     ],
     [
      481,
      508
     ],
     [
      481,
      514
     ],
     [
      482,
      520
     ],
     [
      483,
      526
     ],
     [
      483,
      532
     ],
     [
      483,
      538
     ],
     [
      483,
      544
     ],
     [
      484,
      550
     ],
     [
      486,
      556
     ],
     [
      488,
      562
     ],
     [
      490,
      568
     ],
     [
      493,
      574
     ],
     [
      497,
      580
     ],
     [
      501,
      586
     ],
     [
      504,
      592
     ],
     [
      506,
      598
     ],
     [
      508,
      604
     ]
    ],
    "length_px": 158,
    "mean_halfwidth_px": 3.0
   },
   {
    "polyline": [
     [
      400,
      482
     ],
     [
      398,
      484
     ],
     [
      396,
      486
     ],
     [
      394,
      488
     ],
     [
      392,
      490
     ],
     [
      391,
      492
     ],
     [
      390,
      494
     ],
     [
      389,
      496
     ],
     [
      387,
      498
     ],
     [
      385,
      500
     ],
     [
      383,
      502
     ],
     [
      382,
      504
     ],
     [
      380,
      506
     ],
     [
      378,
      508
     ],
     [
      377,
      510
     ],
     [
      375,
      512
     ],
     [
      373,
      514
     ],
     [
      372,
      516
     ],
     [
      370,
      518
     ],
     [
      368,
      520
     ],
     [
      367,
      522
     ],
     [
      365,
      524
     ],
     [
      364,
      526
     ],
     [
      362,
      528
     ],
     [
      361,
      530
     ],
     [
      359,
      532
     ]
    ],
    "length_px": 51,
    "mean_halfwidth_px": 3.61
   },
   {
    "polyline": [
     [
      357,
      532
     ],
     [
      352,
      532
     ],
     [
      347,
      533
     ],
     [
      342,
      535
     ],
     [
      337,
      536
     ],
     [
      332,
      536
     ],
     [
      327,
      537
     ],
     [
      322,
      538
     ],
     [
      317,
      538
     ],
     [
      312,
      538
     ],
     [
      307,
      537
     ],
     [
      302,
      535
     ],
     [
      297,
      532
     ],
     [
      292,
      529
     ],
     [
      287,
      526
     ],
     [
      282,
      524
     ],
     [
      277,
      522
     ],
     [
      272,
      521
     ],
     [
      267,
      521
     ],
     [
      262,
      520
     ],
     [
      257,
      520
     ],
     [
      252,
      519
     ],
     [
      247,
      518
     ],
     [
      242,
      516
     ],
     [
      237,
      513
     ],
     [
      232,
      510
     ],
     [
      227,
      506
     ],
     [
      222,
      504
     ],
     [
      217,
      502
     ]
    ],
    "length_px": 141,
    "mean_halfwidth_px": 1.41
   },
   {
    "polyline": [
     [
      358,
      535
     ],
     [
      356,
      538
     ],
     [
      354,
      541
     ],
     [
      353,
      544
     ],
     [
      352,
      547
     ],
     [
      351,
      550
     ],
     [
      349,
      553
     ],
     [
      347,
      556
     ],
     [
      345,
      559
     ],
     [
      342,
      562
     ],
     [
      340,
      564
     ],
     [
      337,
      566
     ],
     [
      335,
      568
     ],
     [
      332,
      571
     ],
     [
      329,
      573
     ],
     [
      326,
      575
     ],
     [
      323,
      578
     ],
     [
      320,
      579
     ],
     [
      317,
      582
     ],
     [
      314,
      585
     ],
     [
      311,
      586
     ],
     [
      309,
      589
     ],
     [
      306,
      591
     ],
     [
      303,
      593
     ],
     [
      300,
      596
     ],
     [
      297,
      598
     ],
     [
      294,
      601
     ],
     [
      291,
      604
     ],
     [
      288,
      607
     ],
     [
      285,
      609
     ],
     [
      282,
      612
     ]
    ],
    "length_px": 93,
    "mean_halfwidth_px": 3.16
   },
   {
    "polyline": [
     [
      83,
      540
     ],
     [
      84,
      541
     ],
     [
      84,
      542
     ],
     [
      85,
      543
     ],
     [
      85,
      544
     ],
     [
      86,
      545
     ],
     [
      87,
      546
     ],
     [
      87,
      547
     ],
     [
      88,
      548
     ],
     [
      88,
      549
     ],
     [
      88,
      550
     ]
    ],
    "length_px": 11,
    "mean_halfwidth_px": 1.0
   },
   {
    "polyline": [
     [
      78,
      554
     ],
     [
      79,
      554
     ],
     [
      80,
      554
     ],
     [
      81,
      554
     ],
     [
      82,
      554
     ],
     [
      83,
      553
     ],
     [
      84,
      553
     ],
     [
      85,
      553
     ],
     [
      86,
      553
     ],
     [
      87,
      553
     ]
    ],
    "length_px": 10,
    "mean_halfwidth_px": 1.0
   },
   {
    "polyline": [
     [
      89,
      553
     ],
     [
      94,
      556
     ],
     [
      99,
      559
     ],
     [
      104,
      561
     ],
     [
      109,
      563
     ],
     [
      114,
      563
     ],
     [
      119,
      564
     ],
     [
      124,
      565
     ],
     [
      129,
      567
     ],
     [
      134,
      568
     ],
     [
      139,
      569
     ],
     [
      144,
      570
     ],
     [
      149,
      570
     ],
     [
      154,
      570
     ],
     [
      159,
      571
     ],
     [
      164,
      572
     ],
     [
      169,
      576
     ],
     [
      174,
      580
     ],
     [
      179,
      584
     ],
     [
      184,
      587
     ],
     [
      189,
      592
     ],
     [
      194,
      596
     ],
     [
      198,
      599
     ],
     [
      203,
      604
     ],
     [
      208,
      606
     ],
     [
      212,
      611
     ],
     [
      217,
      615
     ]
    ],
    "length_px": 132,
    "mean_halfwidth_px": 2.0
   },
   {
    "polyline": [
     [
      512,
      607
     ],
     [
      515,
      608
     ],
     [
      518,
      609
     ],
     [
      521,
      610
     ],
     [
      524,
      612
     ],
     [
      527,
      614
     ],
     [
      530,
      617
     ],
     [
      533,
      619
     ],
     [
      536,
      620
     ],
     [
      539,
      622
     ],
     [
      542,
      624
     ],
     [
      545,
      626
     ],
     [
      548,
      628
     ],
     [
      551,
      630
     ],
     [
      553,
      633
     ],
     [
      556,
      636
     ],
     [
      559,
      638
     ],
     [
      562,
      641
     ],
     [
      564,
      643
     ],
     [
      567,
      646
     ],
     [
      570,
      649
     ],
     [
      573,
      651
     ],
     [
      576,
      653
     ],
     [
      578,
      656
     ],
     [
      581,
      659
     ],
     [
      584,
      661
     ]
    ],
    "length_px": 77,
    "mean_halfwidth_px": 1.41
   },
   {
    "polyline": [
     [
      508,
      608
     ],
     [
      507,
      613
     ],
     [
      507,
      618
     ],
     [
      507,
      623
     ],
     [
      505,
      628
     ],
     [
      505,
      633
     ],
     [
      504,
      638
     ],
     [
      503,
      643
     ],
     [
      502,
      648
     ],
     [
      500,
      653
     ],
     [
      498,
      658
     ],
     [
      496,
      663
     ],
     [
      494,
      668
     ],
     [
      491,
      673
     ],
     [
      489,
      678
     ],
     [
      488,
      683
     ],
     [
      486,
      688
     ],
     [
      485,
      693
     ],
     [
      484,
      698
     ],
     [
      483,
      703
     ],
     [
      481,
      708
     ],
     [
      478,
      713
     ],
     [
      478,
      718
     ],
     [
      477,
      723
     ],
     [
      476,
      728
     ],
     [
      474,
      733
     ],
     [
      474,
      738
     ]
    ],
    "length_px": 132,
    "mean_halfwidth_px": 1.41
   },
   {
    "polyline": [
     [
      222,
      619
     ],
     [
      224,
      618
     ],
     [
      226,
      618
     ],
     [
      228,
      618
     ],
     [
      230,
      618
     ],
     [
      232,
      618
     ],
     [
      234,
      618
     ],
     [
      236,
      618
     ],
     [
      238,
      618
     ],
     [
      240,
      618
     ],
     [
      242,
      618
     ],
     [
      244,
      618
     ],
     [
      246,
      618
     ],
     [
      248,
      618
     ],
     [
      250,
      618
     ],
     [
      252,
      618
     ],
     [
      254,
      618
     ],
     [
      256,
      618
     ],
     [
      258,
      617
     ],
     [
      260,
      617
     ],
     [
      262,
      617
     ],
     [
      264,
      616
     ],
     [
      266,
      616
     ],
     [
      268,
      615
     ],
     [
      270,
      614
     ],
     [
      272,
      614
     ],
     [
      274,
      614
     ],
     [
      276,
      614
     ]
    ],
    "length_px": 55,
    "mean_halfwidth_px": 3.0
   },
   {
    "polyline": [
     [
      278,
      617
     ],
     [
      278,
      621
     ],
     [
      278,
      625
     ],
     [
      278,
      629
     ],
     [
      279,
      633
     ],
     [
      279,
      637
     ],
     [
      279,
      641
     ],
     [
      279,
      645
     ],
     [
      278,
      649
     ],
     [
      277,
      653
     ],
     [
      276,
      657
     ],
     [
      274,
      661
     ],
     [
      272,
      665
     ],
     [
      268,
      669
     ],
     [
      265,
      673
     ],
     [
      262,
      677
     ],
     [
      258,
      681
     ],
     [
      254,
      684
     ],
     [
      250,
      686
     ],
     [
      246,
      689
     ],
     [
      242,
      693
     ],
     [
      238,
      695
     ],
     [
      234,
      698
     ],
     [
      230,
      701
     ],
     [
      226,
      704
     ],
     [
      222,
      706
     ],
     [
      218,
      707
     ],
     [
      214,
      709
     ],
     [
      210,
      711
     ]
    ],
    "length_px": 113,
    "mean_halfwidth_px": 2.24
   },
   {
    "polyline": [
     [
      218,
      620
     ],
     [
      214,
      622
     ],
     [
      210,
      623
     ],
     [
      206,
      624
     ],
     [
      202,
      624
     ],
     [
      198,
      624
     ],
     [
      194,
      623
     ],
     [
      190,
      624
     ],
     [
      186,
      623
     ],
     [
      182,
      622
     ],
     [
      178,
      622
     ],
     [
      174,
      622
     ],
     [
      170,
      623
     ],
     [
      166,
      623
     ],
     [
      162,
      625
     ],
     [
      158,
      626
     ],
     [
      154,
      628
     ],
     [
      150,
      630
     ],
     [
      146,
      633
     ],
     [
      142,
      634
     ],
     [
      138,
      635
     ],
     [
      134,
      637
     ],
     [
      130,
      639
     ],
     [
      126,
      640
     ],
     [
      122,
      641
     ],
     [
      118,
      641
     ],
     [
      114,
      642
     ]
    ],
    "length_px": 105,
    "mean_halfwidth_px": 2.0
   }
  ],
  "n_endpoints": 48,
  "n_junctions": 87
 },
 "width_profile": {
  "s_px": [
   0.0,
   2.0,
   4.0,
   6.0,
   8.4,
   10.4,
   12.4,
   14.4,
   16.4,
   18.4,
   21.4,
   23.4,
   25.8,
   27.8,
   29.8,
   31.8,
   33.8,
   35.8,
   37.8,
   39.8,
   42.8,
   44.8,
   46.8,
   48.8,
   50.8,
   52.8,
   54.8,
   57.2,
   59.2,
   61.2,
   64.2,
   66.2,
   68.7,
   71.1,
   73.1,
   75.5,
   77.9,
   80.3,
   82.3,
   84.7,
   88.1,
   90.6,
   93.0,
   95.4,
   98.2,
   100.2,
   102.2,
   104.2,
   106.2,
   108.2,
   111.2,
   113.2,
   115.2,
   117.2,
   119.2,
   121.2,
   123.2,
   125.2,
   127.2,
   129.2,
   132.6,
   134.6,
   136.6,
   138.6,
   140.6,
   142.6,
   145.0,
   147.0,
   149.0,
   151.5,
   154.5,
   156.5,
   158.5,
   160.5,
   162.5,
   164.5,
   166.5,
   168.5,
   170.5,
   173.5
  ],
  "w_dt_px": [
   2.0,
   4.0,
   4.0,
   2.83,
   4.0,
   4.0,
   4.0,
   4.0,
   4.0,
   4.0,
   4.0,
   4.0,
   2.0,
   4.0,
   4.0,
   4.0,
   4.0,
   4.0,
   4.0,
   4.0,
   4.0,
   2.83,
   2.0,
   2.0,
   2.0,
   4.0,
   2.0,
   4.0,
   4.0,
   4.0,
   4.0,
   2.83,
   4.0,
   4.0,
   4.0,
   4.0,
   4.47,
   4.0,
   2.83,
   4.0,
   4.0,
   2.83,
   4.0,
   4.0,
   4.47,
   4.47,
   4.0,
   4.0,
   4.0,
   4.0,
   4.0,
   4.0,
   4.0,
   4.0,
   4.0,
   4.0,
   4.0,
   4.0,
   4.0,
   2.83,
   4.0,
   4.0,
   4.0,
   4.0,
   4.0,
   4.0,
   2.0,
   2.0,
   2.0,
   4.0,
   4.0,
   4.0,
   4.0,
   4.0,
   4.0,
   4.0,
   4.0,
   4.0,
   4.0,
   4.0
  ],
  "mm_per_px": null
 },
 "rose": {
  "bins_deg": [
   2.5,
   7.5,
   12.5,
   17.5,
   22.5,
   27.5,
   32.5,
   37.5,
   42.5,
   47.5,
   52.5,
   57.5,
   62.5,
   67.5,
   72.5,
   77.5,
   82.5,
   87.5,
   92.5,
   97.5,
   102.5,
   107.5,
   112.5,
   117.5,
   122.5,
   127.5,
   132.5,
   137.5,
   142.5,
   147.5,
   152.5,
   157.5,
   162.5,
   167.5,
   172.5,
   177.5
  ],
  "weight": [
   528,
   9,
   181,
   290,
   90,
   289,
   58,
   298,
   42,
   202,
   201,
   37,
   114,
   44,
   126,
   85,
   8,
   4,
   413,
   6,
   76,
   132,
   40,
   127,
   40,
   234,
   34,
   188,
   154,
   26,
   138,
   43,
   195,
   135,
   10,
   2
  ]
 },
 "uncertainty": {
  "mean_std": 0.0243,
  "disagree_px": 34810,
  "n_models": 5
 },
 "models": {
  "segformer_b2": {
   "sweep": {
    "tol_px": [
     0,
     1,
     2,
     3,
     4,
     5,
     6,
     7,
     8
    ],
    "f1": [
     0.0,
     0.0,
     0.0,
     0.0,
     0.0,
     0.0,
     0.0,
     0.0,
     0.0
    ]
   },
   "confusion": {
    "tp": 0,
    "fp": 231,
    "fn": 20537,
    "tol_px": 2
   },
   "f1_2px": 0.0,
   "f1_5px": 0.0
  },
  "deeplabv3p_r18": {
   "sweep": {
    "tol_px": [
     0,
     1,
     2,
     3,
     4,
     5,
     6,
     7,
     8
    ],
    "f1": [
     0.0037,
     0.0043,
     0.0047,
     0.0053,
     0.0064,
     0.0082,
     0.0101,
     0.0112,
     0.0131
    ]
   },
   "confusion": {
    "tp": 82,
    "fp": 111,
    "fn": 20488,
    "tol_px": 2
   },
   "f1_2px": 0.004745227462088668,
   "f1_5px": 0.008222083138130588
  },
  "unet_r18": {
   "sweep": {
    "tol_px": [
     0,
     1,
     2,
     3,
     4,
     5,
     6,
     7,
     8
    ],
    "f1": [
     0.0,
     0.0,
     0.0,
     0.0,
     0.0,
     0.0001,
     0.0003,
     0.0005,
     0.0007
    ]
   },
   "confusion": {
    "tp": 0,
    "fp": 2259,
    "fn": 20537,
    "tol_px": 2
   },
   "f1_2px": 0.0,
   "f1_5px": 8.773469029654324e-05
  },
  "hrsegnet_b16": {
   "sweep": {
    "tol_px": [
     0,
     1,
     2,
     3,
     4,
     5,
     6,
     7,
     8
    ],
    "f1": [
     0.0015,
     0.002,
     0.0025,
     0.0032,
     0.0037,
     0.0044,
     0.005,
     0.0055,
     0.0061
    ]
   },
   "confusion": {
    "tp": 56,
    "fp": 17586,
    "fn": 20494,
    "tol_px": 2
   },
   "f1_2px": 0.0025232124014632116,
   "f1_5px": 0.004399495667569815
  },
  "dinov2s14_linear": {
   "sweep": {
    "tol_px": [
     0,
     1,
     2,
     3,
     4,
     5,
     6,
     7,
     8
    ],
    "f1": [
     0.0314,
     0.0387,
     0.0455,
     0.0535,
     0.0608,
     0.0706,
     0.078,
     0.0853,
     0.094
    ]
   },
   "confusion": {
    "tp": 947,
    "fp": 18320,
    "fn": 19666,
    "tol_px": 2
   },
   "f1_2px": 0.04553324948407535,
   "f1_5px": 0.07056095068233327
  }
 }
}